task_cli_tool/__init__.py
task_cli_tool/flow.py
task_cli_tool/nodes.py
task_cli_tool/task_cli_main.py
task_cli_tool/commands/__init__.py
task_cli_tool/commands/decompose.py
task_cli_tool/commands/gantt.py
task_cli_tool/commands/help.py
task_cli_tool/commands/howto.py
task_cli_tool/commands/init.py
task_cli_tool/commands/list.py
task_cli_tool/commands/qa.py
task_cli_tool/commands/report.py
task_cli_tool/commands/update.py
task_cli_tool/templates/gantt_template.html
task_cli_tool/utils/__init__.py
task_cli_tool/utils/call_llm.py
task_cli_tool/utils/display.py
task_cli_tool/utils/llm_api.py
task_cli_tool/utils/storage.py
task_cli_tool-0.0.3.dist-info/licenses/LICENSE
task_cli_tool-0.0.3.dist-info/METADATA
task_cli_tool-0.0.3.dist-info/WHEEL
task_cli_tool-0.0.3.dist-info/entry_points.txt
task_cli_tool-0.0.3.dist-info/top_level.txt
task_cli_tool-0.0.3.dist-info/RECORD
