Metadata-Version: 2.4
Name: task-cli-tool
Version: 0.0.3
Summary: An open-source AI Agent that automatically decomposes tasks, generates Gantt charts, and provides project Q&A within your terminal.
Author-email: sunjiawe <727233543@qq.com>
Project-URL: Homepage, https://github.com/sunjiawe/task-cli
Project-URL: Bug Tracker, https://github.com/sunjiawe/task-cli/issues
Classifier: Programming Language :: Python :: 3
Classifier: License :: OSI Approved :: Apache Software License
Classifier: Operating System :: OS Independent
Requires-Python: >=3.11
License-File: LICENSE
Requires-Dist: pocketflow>=0.0.1
Requires-Dist: rich
Requires-Dist: questionary
Requires-Dist: pyyaml
Requires-Dist: openai
Requires-Dist: python-dotenv
Dynamic: license-file
